begentle/__init__.py
begentle-0.1.1.dist-info/LICENSE
begentle-0.1.1.dist-info/WHEEL
begentle-0.1.1.dist-info/METADATA
begentle-0.1.1.dist-info/RECORD
